<?xml version="1.0" encoding="utf-8" ?>
<dwsync>
<file name="aspect.js" server="213.171.193.5/htdocs/" local="128745721900000000" remote="129292086000000000" />
<file name="docs.js" server="213.171.193.5/htdocs/" local="128987972620000000" remote="129292086000000000" />
<file name="functional.js" server="213.171.193.5/htdocs/" local="128416580810000000" remote="129292086000000000" />
<file name="LICENSE" server="213.171.193.5/htdocs/" local="128388432220000000" remote="129292086000000000" />
<file name="observable.js" server="213.171.193.5/htdocs/" local="128722158850000000" remote="129292086000000000" />
<file name="README" server="213.171.193.5/htdocs/" local="128831583820000000" remote="129292086000000000" />
<file name="typed.js" server="213.171.193.5/htdocs/" local="128987972620000000" remote="129292086000000000" />
<file name="utils.js" server="213.171.193.5/htdocs/" local="128715605690000000" remote="129292086000000000" />
</dwsync>